ctensor.cpython-311-x86_64-linux-gnu.so
llmgrad-0.0.1.dist-info/WHEEL
llmgrad-0.0.1.dist-info/top_level.txt
llmgrad-0.0.1.dist-info/METADATA
llmgrad-0.0.1.dist-info/RECORD
llmgrad/nn.py
llmgrad/optim.py
llmgrad/__init__.py
