Metadata-Version: 2.4
Name: llmgrad
Version: 0.0.1
Summary: A C++ AI engine with Python bindings
Author: user447-ui
Author-email: user447-ui <secretmail294@gmail.com>
License: MIT
Requires-Python: >=3.7
Dynamic: author
Dynamic: requires-python
